{
	"namespace": "logins",
	"include": ["Kernel", "Dbs", "GameApps", "MsgDef","Msgs"],
	"filename": "Logins",
	"msgs": [{
		"id": "342",
		"msg": [{
			"name": "username_",
			"id": 1,
			"type": "string"
		}, {
			"name": "gameChannel_",
			"id": 2,
			"type": "string"
		}, {
			"name": "channelId_",
			"id": 3,
			"type": "string"
		}, {
			"name": "time_",
			"id": 4,
			"type": "int32_t"
		}, {
			"name": "flag_",
			"id": 5,
			"type": "string"
		}, {
			"name": "version_",
			"id": 6,
			"type": "string"
		}, {
			"name": "serverId_",
			"id": 7,
			"type": "int32_t"
		}, {
			"name": "json_",
			"id": 8,
			"type": "string"
		}],
		"name": "SQuery"
	}, {
		"id": "343",
		"msg": [{
			"name": "proxyId_",
			"id": 1,
			"type": "uint16_t"
		}, {
			"name": "serverId_",
			"id": 2,
			"type": "uint16_t"
		}, {
			"name": "playerList_",
			"id": 3,
			"type": "vector<dbs::TPlayer>"
		}],
		"name": "SQueryResult"
	}, {
		"id": "344",
		"msg": [{
			"name": "username_",
			"id": 1,
			"type": "string"
		}, {
			"name": "gameChannel_",
			"id": 2,
			"type": "string"
		}, {
			"name": "channelId_",
			"id": 3,
			"type": "string"
		}, {
			"name": "time_",
			"id": 4,
			"type": "int32_t"
		}, {
			"name": "flag_",
			"id": 5,
			"type": "string"
		}, {
			"name": "version_",
			"id": 6,
			"type": "string"
		}, {
			"name": "playerId_",
			"id": 7,
			"type": "int32_t"
		}, {
			"name": "name_",
			"id": 8,
			"type": "string"
		}, {
			"name": "sex_",
			"id": 9,
			"type": "int16_t"
		}, {
			"name": "career_",
			"id": 10,
			"type": "int16_t"
		}, {
			"name": "sdkTime_",
			"id": 11,
			"type": "int32_t"
		}, {
			"name": "platformExtend_",
			"id": 12,
			"type": "string"
		}, {
			"name": "serverId_",
			"id": 13,
			"type": "int32_t"
		}, {
			"name": "json_",
			"id": 14,
			"type": "string"
		}],
		"name": "SLogin"
	}, {
		"id": "345",
		"msg": [{
			"name": "gateHost_",
			"id": 1,
			"type": "string"
		}, {
			"name": "gatePort_",
			"id": 2,
			"type": "int32_t"
		}, {
			"name": "token_",
			"id": 3,
			"type": "string"
		}, {
			"name": "proxyId_",
			"id": 4,
			"type": "uint16_t"
		}, {
			"name": "serverId_",
			"id": 5,
			"type": "uint16_t"
		}, {
			"name": "player_",
			"id": 6,
			"type": "dbs::TPlayer"
		}],
		"name": "SLoginResult"
	}, {
		"id": "346",
		"msg": [{
			"name": "clientTs_",
			"id": 1,
			"type": "int64_t"
		}, {
			"name": "extend_",
			"id": 2,
			"type": "string"
		}],
		"name": "SLoginPing"
	}, {
		"id": "347",
		"msg": [{
			"name": "clientTs_",
			"id": 1,
			"type": "int64_t"
		}, {
			"name": "serverTs_",
			"id": 2,
			"type": "int64_t"
		}],
		"name": "SLoginPong"
	}, {
		"id": "348",
		"msg": [{
			"name": "cmds_",
			"id": 1,
			"type": "vector<int32_t>"
		}],
		"name": "SQueryGameData"
	}, {
		"id": "349",
		"msg": [{
			"name": "entityId_",
			"id": 1,
			"type": "Identity"
		}, {
			"name": "operTime_",
			"id": 2,
			"type": "int64_t"
		}, {
			"name": "moveId_",
			"id": 3,
			"type": "uint16_t"
		}, {
			"name": "path_",
			"id": 4,
			"type": "vector<Point>"
		}],
		"name": "SRoleMove"
	}, {
		"id": "350",
		"msg": [],
		"name": "SEnterHang"
	}, {
		"id": "351",
		"msg": [],
		"name": "SBackToCity"
	}, {
		"id": "352",
		"msg": [{
			"name": "monsters_",
			"id": 1,
			"type": "map<int32_t, int32_t>"
		}],
		"name": "SBatchFightResultReq"
	}, {
		"id": "353",
		"msg": [{
			"name": "canRefreshElite_",
			"id": 1,
			"type": "bool"
		}],
		"name": "SBatchFightResultResp"
	}, {
		"id": "354",
		"msg": [{
			"name": "resetPoints_",
			"id": 1,
			"type": "vector<Point>"
		}],
		"name": "SHangChallengeBoss"
	}, {
		"id": "355",
		"msg": [{
			"name": "roleId_",
			"id": 1,
			"type": "int32_t"
		}, {
			"name": "oper_",
			"id": 2,
			"type": "igameapp::SFightOper"
		}, {
			"name": "skillUid_",
			"id": 3,
			"type": "int16_t"
		}, {
			"name": "noCd_",
			"id": 4,
			"type": "bool"
		}],
		"name": "SUseSkill"
	}, {
		"id": "356",
		"msg": [{
			"name": "monsterId_",
			"id": 1,
			"type": "int32_t"
		}, {
			"name": "killPoint_",
			"id": 2,
			"type": "Point"
		}],
		"name": "SFightResultReq"
	}, {
		"id": "366",
		"msg": [{
			"name": "entityId_",
			"id": 1,
			"type": "Identity"
		}, {
			"name": "operTime_",
			"id": 2,
			"type": "int64_t"
		}, {
			"name": "moveId_",
			"id": 3,
			"type": "uint16_t"
		}, {
			"name": "jumpId_",
			"id": 4,
			"type": "string"
		}, {
			"name": "isReverse_",
			"id": 5,
			"type": "bool"
		}],
		"name": "SMapJump"
	}, {
		"id": "367",
		"msg": [{
			"name": "operTime_",
			"id": 1,
			"type": "int64_t"
		}, {
			"name": "passType_",
			"id": 2,
			"type": "int32_t"
		}, {
			"name": "passId_",
			"id": 3,
			"type": "int32_t"
		}, {
			"name": "passToId_",
			"id": 4,
			"type": "int32_t"
		}],
		"name": "SMapTransfer"
	}, {
		"id": "368",
		"msg": [{
			"name": "missionId_",
			"id": 1,
			"type": "int32_t"
		}],
		"name": "SMissionReq"
	}, {
		"id": "369",
		"msg": [{
			"name": "missionId_",
			"id": 1,
			"type": "int32_t"
		}],
		"name": "SMissionCommit"
	}, {
		"id": "370",
		"msg": [{
			"name": "roleId_",
			"id": 1,
			"type": "int32_t"
		}, {
			"name": "type_",
			"id": 2,
			"type": "int32_t"
		}],
		"name": "SActiveAdvance"
	}, {
		"id": "371",
		"name": "SUpgradeSkill",
		"msg": [
			{"name": "roleId_", "id":1, "type":"int32_t"},
			{"name": "skillId_", "id":1, "type":"int32_t"}
		]
	}, {
		"id": "519",
		"name": "SAdvanceReq",
		"msg": [
			{"name":"roleId_", "id":1, "type": "int32_t"},
			{"name":"type_", "id":2, "type": "int32_t"},
			{"name":"itemId_", "id":3, "type": "int32_t"},
			{"name":"autoBuy_", "id":4, "type": "bool"}
		]
	}, {
		"id": "373",
		"name": "SAdvanceResp",
		"msg": [
			{"name":"success_", "id":1, "type": "bool"},
			{"name":"activeMul_", "id":2, "type": "int32_t"}
		]
	}, {
		"id": "374",
		"name": "SAdvanceEatDan",
		"msg": [
			{"name":"roleId_", "id":1, "type": "int32_t"},
			{"name":"type_", "id":2, "type": "int32_t"},
			{"name":"itemId_", "id":3, "type": "int32_t"}
		]
	}, {
		"id": "1699",
		"name": "SBagDecompose",
		"msg":	[
			{"name":"uidList", "id":1, "type": "vector<int64_t>"}
		]
	}, {
		"id": "375",
		"name": "SShenQiPiece",
		"msg": [
			{"name":"itemId_", "id":1, "type": "int32_t"}
		]
	}, {
		"id": "376",
		"name": "SShenQi",
		"msg": []
	}, {
		"id": "377",
		"name": "SUpgradeSkillAll",
		"msg": [
			{"name":"roleId_", "id":1, "type": "int32_t"}
		]
	}, {
		"id": "378",
		"name": "SEquipEquip",
		"msg": [
			{"name":"roleId_", "id":1, "type": "int32_t"},
			{"name":"uds_", "id":2, "type": "vector<int64_t>"}
		]
	}, {
		"id": "379",
		"name": "SBagOpenGrid",
		"msg": [
			{"name":"bagType_", "id":1, "type": "int32_t"},
			{"name":"gridId_", "id":2, "type": "int32_t"},
			{"name":"gridNum_", "id":3, "type": "int32_t"}
		]
	}, {
		"id": "1773",
		"name": "SActiveTreasure",
		"msg": [
			{"name":"type_", "id":1, "type": "int32_t"}
		]
	}, {
		"id": "1754",
		"name": "STreasureAdvance",
		"msg": [
			{"name":"type_", "id":1, "type": "int32_t"},
			{"name":"itemId_", "id":2, "type": "int32_t"}
		]
	}, {
		"id": "1771",
		"name": "STreasureEatDan",
		"msg": [
			{"name":"type_", "id":1, "type": "int32_t"},
			{"name":"itemId_", "id":2, "type": "int32_t"}
		]
	}, {
		"id": "422",
		"name": "SBagUse",
		"msg": [
			{"name":"bagType_", "id":1, "type": "int32_t"},
			{"name":"itemUid_", "id":2, "type": "int64_t"},
			{"name":"itemNum_", "id":3, "type": "int32_t"},
			{"name":"value_", "id":4, "type": "int32_t"}
		]
	}, {
		"id": "1053",
		"name": "SStrengthenReq",
		"msg": [
			{"name":"roleId_", "id":1, "type": "int32_t"},
			{"name":"equipType_", "id":2, "type": "vector<int32_t>"},
			{"name":"toLevel_", "id":3, "type": "int32_t"}
		]
	}, {
		"id": "1053",
		"name": "SStrengthenResp",
		"msg": [
			{"name":"equip_", "id":1, "type": "vector<dbs::TPlayerEquip>"}
		]
	}, {
		"id": "599",
		"name": "SAdvanceRide",
		"msg": [
			{"name":"ride_", "id":1, "type": "bool"}
		]
	}, {
		"id": "2222",
		"name": "SPurifyReq",
		"msg": [
			{"name":"roleId_", "id":1, "type": "int32_t"},
			{"name":"equipType_", "id":2, "type": "vector<int32_t>"}
		]
	}, {
		"id": "2222",
		"name": "SPurifyResp",
		"msg": [
			{"name":"equip_", "id":1, "type": "vector<dbs::TPlayerEquip>"}
		]
	}
	, {
		"id": "1037",
		"name": "CEmbedGemReq",
		"msg": [
			{"name":"roleId_", "id":1, "type": "int32_t"},
			{"name":"equipType_", "id":2, "type": "int32_t"},
			{"name": "gemUidSlot_", "id":3, "type": "map<int32_t, int64_t>"}
		]
	}, {
		"id": "1037",
		"name": "SEmbedGemResp",
		"msg": [
			{"name":"tPlayerEquip_", "id":1, "type": "dbs::TPlayerEquip"}
		]
	}
	, {
		"id": "1056",
		"name": "CRemoveGemReq",
		"msg": [
			{"name":"roleId_", "id":1, "type": "int32_t"},
			{"name":"equipType_", "id":2, "type": "int32_t"},
			{"name":"gemSlot_", "id":3, "type": "int32_t"}
		]
	}, {
		"id": "1056",
		"name": "SRemoveGemResp",
		"msg": [
			{"name":"tPlayerEquip_", "id":1, "type": "dbs::TPlayerEquip"}
		]
	}
	, {
		"id": "1057",
		"name": "CctivateGemTargetReq",
		"msg": [
			{"name":"roleId_", "id":1, "type": "int32_t"},
			{"name":"targetId_", "id":2, "type": "int32_t"}
		]
	}
	, {
		"id": "1120",
		"name": "CUpgradeGemReq",
		"msg": [
			{"name":"roleId_", "id":1, "type": "int32_t"},
			{"name":"equipType_", "id":2, "type": "int32_t"},
			{"name":"gemSlot_", "id":3, "type": "vector<int32_t>"}
		]
	}, {
		"id": "1120",
		"name": "SUpgradeGemResp",
		"msg": [
			{"name":"tPlayerEquip_", "id":1, "type": "dbs::TPlayerEquip"}
		]
	}
	, {
		"id": "1077",
		"name": "STitleReq",
		"msg": [
			{"name":"roleId_", "id":1, "type": "int32_t"},
			{"name":"titleId_", "id":2, "type": "int32_t"}
		]
	}, {
		"id": "4071",
		"name": "COnlineRewardReq",
		"msg": [
			{"name":"onlineTime_", "id":1, "type": "int32_t"}
		]
	}, {
		"id": "1418",
		"name": "CActiveFashionReq",
		"msg": [
			{"name":"roleId_", "id":1, "type": "int32_t"},
			{"name":"type_", "id":2, "type": "int32_t"},
			{"name":"fashionId_", "id":3, "type": "int32_t"}
		]
	}, {
		"id": "2046",
		"name": "CAdvanceFashionReq",
		"msg": [
			{"name":"roleId_", "id":1, "type": "int32_t"},
			{"name":"type_", "id":2, "type": "int32_t"},
			{"name":"fashionId_", "id":3, "type": "int32_t"}
		]
	}, 
	{
		"id": "2047",
		"name": "CPutOnFashionReq",
		"msg": [
			{"name":"roleId_", "id":1, "type": "int32_t"},
			{"name":"type_", "id":2, "type": "int32_t"},
			{"name":"fashionId_", "id":3, "type": "int32_t"}
		]
	}, {
		"id": "2047",
		"name": "SPutOnFashionResp",
		"msg": [
			{"name":"fashionId_", "id":1, "type": "int32_t"}
		]
	}, {
		"id": "2048",
		"name": "CGetOffFashionReq",
		"msg": [
			{"name":"roleId_", "id":1, "type": "int32_t"},
			{"name":"type_", "id":2, "type": "int32_t"},
			{"name":"fashionId_", "id":3, "type": "int32_t"}
		]
	}, {
		"id": "2048",
		"name": "SGetOffFashionResp",
		"msg": [
			{"name":"fashionId_", "id":1, "type": "int32_t"}
		]
	}
	, {
		"id": "3742",
		"name": "CActiveFashionSuitReq",
		"msg": [
			{"name":"roleId_", "id":1, "type": "int32_t"},
			{"name":"suitId_", "id":2, "type": "int32_t"},
			{"name":"num_", "id":3, "type": "int32_t"}
		]
	}
	, {
		"id": "3742",
		"name": "SActiveFashionSuitResp",
		"msg": [{
			"name": "suits_","id": 1,"type": "map<int32_t, msgs::SInts>"
		}]
	}
	, {
		"id": "3077",
		"name": "SActiveSuitReq",
		"msg": [
			{"name":"roleId_", "id":1, "type": "int32_t"},
			{"name":"suitId_", "id":2, "type": "int32_t"},
			{"name":"uids_", "id":3, "type": "vector<int64_t>"}
		]
	}, {
		"id": "3085",
		"name": "SUnlockSuitReq",
		"msg": [
			{"name":"roleId_", "id":1, "type": "int32_t"},
			{"name":"suitId_", "id":2, "type": "int32_t"}
		]
	}, {
		"id": "3086",
		"name": "SDressSuitReq",
		"msg": [
			{"name":"roleId_", "id":1, "type": "int32_t"},
			{"name":"suitId_", "id":2, "type": "int32_t"},
			{"name":"isDress_", "id":3, "type": "bool"}
		]
	}, {
		"id": "1486",
		"name": "STreasureDrawReq",
		"msg": [
			{"name":"type_", "id":1, "type": "int32_t"},
			{"name":"drewNum_", "id":2, "type": "int32_t"}
		]
	}, {
		"id": "1486",
		"name": "STreasureDrawResp",
		"msg": [
			{"name":"drawIds_", "id":1, "type": "vector<int32_t>"},
			{"name":"rewards_", "id":2, "type": "vector<int32_t>"}
		]
	}, {
		"id": "1519",
		"name": "STreasureGetRewardHisReq",
		"msg": [
			{"name":"type_", "id":1, "type": "int32_t"}
		]
	}, {
		"id": "1519",
		"name": "STreasureGetRewardHisResp",
		"msg": [
			{"name":"records_", "id":1, "type": "vector<dbs::TTreasureRecord>"}
		]
	}, {
		"id": "425",
		"name": "SBagMoveItem",
		"msg": [
			{"name":"fromBagType_", "id":1, "type": "int32_t"},
			{"name":"toBagType_", "id":2, "type": "int32_t"},
			{"name":"itemUid_", "id":3, "type": "int64_t"}
		]
	}, {
		"id": "2018",
		"name": "SBagMoveItemAll",
		"msg": [
			{"name":"fromBagType_", "id":1, "type": "int32_t"},
			{"name":"toBagType_", "id":2, "type": "int32_t"}
		]
	}, {
		"id": "2809",
		"name": "SGetActivityReq",
		"msg": [
			{"name":"id_", "id":1, "type": "int32_t"},
			{"name":"count_", "id":2, "type": "int32_t"}
		]
	}, {
		"id": "1127",
		"name": "SGetActivityRewardReq",
		"msg": [
			{"name":"id_", "id":1, "type": "int32_t"}
		]
	}, {
		"id": "2577",
		"name": "SzhulingUpLevelReq",
		"msg": [
			{"name":"roleId_", "id":1, "type": "int32_t"}, 
			{"name":"equipType_", "id":2, "type": "int32_t"},
			{"name":"isAuto_", "id":3, "type": "bool"}
		]
	}, {
		"id": "2577",
		"name": "SzhulingUpLevelResp",
		"msg": [
			{"name":"plyerEquip", "id":1, "type": "dbs::TPlayerEquip"}
		]
	}, {
		"id": "2585",
		"name": "SzhulingUpAdvanceReq",
		"msg": [
			{"name":"roleId_", "id":1, "type": "int32_t"}, 
			{"name":"equipType_", "id":2, "type": "int32_t"}
		]
	}, {
		"id": "2585",
		"name": "SzhulingUpAdvanceResp",
		"msg": [
			{"name":"PlayerEquip", "id":1, "type": "dbs::TPlayerEquip"}
		]
	}, {
		"id": "3493",
		"name": "SopenZhulingReq",
		"msg": [
			{"name":"roleId_", "id":1, "type": "int32_t"}
		]
	}, {
		"id": "2069",
		"name": "SSkillCleanNuQi",
		"msg": []
	}, {
		"id": "481",
		"name": "SBuyReq",
		"msg": [
			{"name":"id", "id":1, "type": "int32_t"},
			{"name":"itemId", "id":2, "type": "int32_t"},
			{"name":"realPrice", "id":3, "type": "int32_t"},
			{"name":"num", "id":4, "type": "int32_t"}
		]
	}, {
		"id": "2244",
		"name": "SDevilAngelequipReq",
		"msg": [
			{"name":"uid", "id":1, "type": "int32_t"},
			{"name":"roleId", "id":2, "type": "int32_t"}
		]
	},{
		"id": "1407",	
		"name": "SPlayerSignEveryDayReq", 
		"msg" :[
			{"name":"flag_", "id":1, "type":"int16_t"}		
		]
	},{
		"id": "1884",
		"name": "SGetSignEverydayRwardReq",
		"msg" :[
			{"name":"day_", "id":1, "type":"int16_t"}		
		]		
	},{
		"id": "1360",
		"name": "SGetLevelRwardReq",
		"msg" :[
			{"name":"careerLevel", "id":1, "type":"int32_t"},	
			{"name":"level", "id":2, "type":"int32_t"}		
		]
	},{
		"id":"1898",
		"name": "STrumpActiveReq",
		"msg" : [
			{"name": "subtype", "id":1, "type":"int32_t"},
			{"name": "id", "id": 1, "type": "int32_t"}	
		]
	},{
		"id":"4405",
		"name": "SCommitShengMissionReq",
		"msg" : [
			{"name": "missionId", "id": 1, "type": "int32_t"}	
		]
	},{
		"id":"4404",
		"name": "SRequestShengMissionReq",
		"msg" : [	
		]
	},{
		"id":"1899",
		"name": "STrumpUpgradeReq",
		"msg" : [
			{"name": "count", "id":1, "type":"int32_t" }
		]
	},{
		"id":"1992",
		"name": "SActiveTrumpSkillReq",
		"msg" : [
			{"name": "level", "id":1, "type":"int32_t" }
		]
	},{
		"id":"3507",
		"name": "STrumpRequestMissionReq",
		"msg" : [
			{"name": "missionId", "id":1, "type":"int32_t" }
		]
	},{
		"id":"1965",
		"name": "SUnlockTrumpReq",
		"msg" : [
		]
	},{
		"id":"571",
		"name": "SDressReq",
		"msg" : [
			{"name": "roleId", "id":1, "type":"int32_t" },
			{"name": "uid", "id":2, "type":"int64_t" }
		]
	},{
		"id":"1889",
		"name": "SStrengthEquipReq",
		"msg" : [
			{"name": "roleId", "id":1, "type":"int32_t" },
			{"name": "type", "id":2, "type":"int32_t" },
			{"name": "uid", "id":3, "type":"int64_t" }
		]
	},{
		"id":"2586",
		"name": "SOneKeyDressReq",
		"msg" : [
			{"name": "roleId", "id":1, "type":"int32_t" },
			{"name": "type", "id":2, "type":"int32_t" },
			{"name":"uids", "id":3, "type": "vector<int64_t>"}
		]
	},{
		"id":"883",
		"name": "SRecycleReq",
		"msg" : [
			{"name": "items", "id":1, "type": "map<int64_t, int32_t>"}
		]
	},{
		"id":"1891",
		"name": "SLearnSkillReq",
		"msg" : [
			{"name": "roleId", "id":1, "type":"int32_t" },
			{"name": "type", "id":2, "type":"int32_t" },
			{"name": "skillId", "id":3, "type":"int32_t" }
		]
	},{
		"id":"3106",
		"name": "SAdvanceAwakenReq",
		"msg" : [
			{"name": "roleId", "id":1, "type": "int32_t"},
			{"name": "type", "id":2, "type": "int32_t"},
			{"name": "autoBuy", "id":4, "type": "bool"}
		]
	},{
		"id":"3340",
		"name": "SActiveAdvanceTargetReq",
		"msg" : [
			{"name": "type", "id":1, "type": "int32_t"},
			{"name": "targetLevel", "id":2, "type": "int32_t"}
		]
	},{
		"id":"1922",
		"name": "SCardUpStarReq",
		"msg" : [
			{"name": "uid", "id":1, "type": "int64_t"}
		]
	},{
		"id":"1894",
		"name": "SEquipZhanlingReq",
		"msg" : [
			{"name": "uid", "id":1, "type": "int64_t"}
		]
	},{
		"id":"1893",
		"name": "SAdvanceZhanlingReq",
		"msg" : [
		]
	},{
		"id":"3506",
		"name": "SLearnZhanlingSkillReq",
		"msg" : [
			{"name": "skillId", "id":1, "type": "int32_t"}
		]
	},{
        "id":"2152",
		"name": "SNearenmeyFightenemyReq",
		"msg" : [
			{"name": "playerId", "id":1, "type": "int32_t"},
            {"name": "oldPoints", "id":1, "type": "vector<Point>"}
        ]
    },{
		"id":"2191",
		"name": "SNearenemyBacktoHangReq",
		"msg" : [
		]    
    },{
		"id":"747",
		"name": "SGetTopListReq",
		"msg" : [
			{"name": "toplistType", "id":1, "type": "int32_t"}
		]    
    }
	
	]
}